fairness/__init__.py
fairness/analysis.py
fairness/benchmark.py
fairness/get_best_split.py
fairness/preprocess.py
fairness/results.py
fairness/algorithms/Algorithm.py
fairness/algorithms/ParamGridSearch.py
fairness/algorithms/__init__.py
fairness/algorithms/list.py
fairness/algorithms/Ben/SDBAdaBoost.py
fairness/algorithms/Ben/SDBSVM.py
fairness/algorithms/Ben/__init__.py
fairness/algorithms/Ben/boosting.py
fairness/algorithms/Ben/errorfunctions.py
fairness/algorithms/Ben/lr.py
fairness/algorithms/Ben/margin.py
fairness/algorithms/Ben/svm.py
fairness/algorithms/Ben/utils.py
fairness/algorithms/Ben/weaklearners/__init__.py
fairness/algorithms/Ben/weaklearners/decisionstump.py
fairness/algorithms/Ben/weaklearners/decisiontree.py
fairness/algorithms/Ben/weaklearners/nearestneighbor.py
fairness/algorithms/baseline/DecisionTree.py
fairness/algorithms/baseline/GaussianNB.py
fairness/algorithms/baseline/Generic.py
fairness/algorithms/baseline/LogisticRegression.py
fairness/algorithms/baseline/SVM.py
fairness/algorithms/baseline/__init__.py
fairness/algorithms/feldman/FeldmanAlgorithm.py
fairness/algorithms/feldman/__init__.py
fairness/algorithms/kamishima/CaldersAlgorithm.py
fairness/algorithms/kamishima/KamishimaAlgorithm.py
fairness/algorithms/kamishima/__init__.py
fairness/algorithms/kamishima/kamfadm-2012ecmlpkdd/commands.py
fairness/algorithms/kamishima/kamfadm-2012ecmlpkdd/fai_bin_bin.py
fairness/algorithms/kamishima/kamfadm-2012ecmlpkdd/predict_lr.py
fairness/algorithms/kamishima/kamfadm-2012ecmlpkdd/predict_nb.py
fairness/algorithms/kamishima/kamfadm-2012ecmlpkdd/train_cv2nb.py
fairness/algorithms/kamishima/kamfadm-2012ecmlpkdd/train_lr.py
fairness/algorithms/kamishima/kamfadm-2012ecmlpkdd/train_nb.py
fairness/algorithms/kamishima/kamfadm-2012ecmlpkdd/train_pr.py
fairness/algorithms/kamishima/kamfadm-2012ecmlpkdd/data/add_quad_terms.py
fairness/algorithms/kamishima/kamfadm-2012ecmlpkdd/data/adult_arff.py
fairness_cscheid-0.1.7.dist-info/AUTHORS.txt
fairness_cscheid-0.1.7.dist-info/LICENSE.txt
fairness_cscheid-0.1.7.dist-info/METADATA
fairness_cscheid-0.1.7.dist-info/WHEEL
fairness_cscheid-0.1.7.dist-info/top_level.txt
fairness_cscheid-0.1.7.dist-info/RECORD
