Metadata-Version: 2.1
Name: fairness-cscheid
Version: 0.1.7
Summary: Fairness-aware machine learning: algorithms, comparisons, benchmarking
Home-page: https://github.com/algofairness/fairness-comparison
Author: See Authors.txt
Author-email: fairness@haverford.edu
License: Apache 2.0
Platform: UNKNOWN
Classifier: Programming Language :: Python :: 3
Classifier: License :: OSI Approved :: Apache Software License
Classifier: Operating System :: OS Independent
Requires-Dist: BlackBoxAuditing (>=0.1.26ggplot)
Requires-Dist: fire
Requires-Dist: pandas (>=0.21.1)
Requires-Dist: pyparsing (>=2.1.4)
Requires-Dist: python-dateutil (>=2.6.0)
Requires-Dist: pytz
Requires-Dist: scikit-learn (>=0.18.1)
Requires-Dist: scipy (>=0.19.0)
Requires-Dist: six (>=1.10.0)
Requires-Dist: wheel (>=0.29.0)
